mstuff/__init__.py
mstuff/argparser.py
mstuff/http.py
mstuff/mstuff.py
mstuff-0.7.12.dist-info/METADATA
mstuff-0.7.12.dist-info/WHEEL
mstuff-0.7.12.dist-info/top_level.txt
mstuff-0.7.12.dist-info/RECORD
